taters/Taters.py
taters/__init__.py
taters/audio/__init__.py
taters/audio/analyze_vocal_acoustics.py
taters/audio/convert_to_wav.py
taters/audio/diarize_with_thirdparty.py
taters/audio/extract_wav_from_video.py
taters/audio/extract_whisper_embeddings.py
taters/audio/extract_whisper_embeddings_subproc.py
taters/audio/split_wav_by_speaker.py
taters/audio/diarizer/__init__.py
taters/audio/diarizer/whisper_diar_wrapper.py
taters/audio/diarizer/whisper-diarization/__init__.py
taters/audio/diarizer/whisper-diarization/constraints.txt
taters/audio/diarizer/whisper-diarization/diarize.py
taters/audio/diarizer/whisper-diarization/diarize_custom.py
taters/audio/diarizer/whisper-diarization/diarize_parallel.py
taters/audio/diarizer/whisper-diarization/helpers.py
taters/audio/diarizer/whisper-diarization/requirements.txt
taters/audio/diarizer/whisper-diarization/setup.cfg
taters/audio/diarizer/whisper-diarization/diarization/__init__.py
taters/audio/diarizer/whisper-diarization/diarization/msdd/diar_infer_telephonic.yaml
taters/audio/diarizer/whisper-diarization/diarization/msdd/msdd.py
taters/audio/diarizer/whisper-diarization/diarization/msdd/msdd_custom.py
taters/helpers/__init__.py
taters/helpers/feature_gather.py
taters/helpers/find_files.py
taters/helpers/text_gather.py
taters/pipelines/__init__.py
taters/pipelines/run_pipeline.py
taters/pipelines/presets/conversation_video.yaml
taters/text/__init__.py
taters/text/analyze_lexical_richness.py
taters/text/analyze_readability.py
taters/text/analyze_with_archetypes.py
taters/text/analyze_with_dictionaries.py
taters/text/extract_sentence_embeddings.py
taters/text/subtitle_parser.py
taters/text/dictionary_analyzers/__init__.py
taters/text/dictionary_analyzers/multi_archetype_analyzer.py
taters/text/dictionary_analyzers/multi_dict_analyzer.py
taters/video/__init__.py
taters/video/extract_features.py
taters/video/features_basic.py
taters/video/features_motion.py
taters/video/features_ocr.py
taters/video/features_shots.py
taters-0.1.95.dist-info/licenses/LICENSE
taters-0.1.95.dist-info/METADATA
taters-0.1.95.dist-info/WHEEL
taters-0.1.95.dist-info/entry_points.txt
taters-0.1.95.dist-info/top_level.txt
taters-0.1.95.dist-info/RECORD
