Metadata-Version: 2.4
Name: taters
Version: 0.1.95
Summary: Analyze, process, and extract from many types of input data. Highly modular/customizable.
Author-email: "Ryan L. Boyd" <ryan@ryanboyd.io>
License: MIT
Project-URL: Homepage, https://github.com/ryanboyd/taters
Project-URL: Issues, https://github.com/ryanboyd/taters/issues
Classifier: Programming Language :: Python :: 3
Classifier: License :: OSI Approved :: MIT License
Classifier: Operating System :: OS Independent
Classifier: Topic :: Multimedia :: Sound/Audio :: Analysis
Classifier: Intended Audience :: Science/Research
Requires-Python: >=3.10
License-File: LICENSE
Requires-Dist: faster-whisper>=1.1.0
Requires-Dist: transformers>=4.38.0
Requires-Dist: librosa>=0.10.1
Requires-Dist: pydub>=0.25.1
Requires-Dist: contentcoder
Requires-Dist: archetyper
Requires-Dist: nltk
Requires-Dist: sentence-transformers
Provides-Extra: all
Requires-Dist: nemo-toolkit[asr]>=2.dev; extra == "all"
Requires-Dist: nvidia-cudnn-cu12; extra == "all"
Requires-Dist: textstat<0.8,>=0.7; extra == "all"
Requires-Dist: praat-parselmouth>=0.4.6; extra == "all"
Requires-Dist: disvoice>=0.1.10; extra == "all"
Provides-Extra: diarization
Requires-Dist: nemo-toolkit[asr]>=2.dev; extra == "diarization"
Provides-Extra: cuda
Requires-Dist: nvidia-cudnn-cu12; extra == "cuda"
Provides-Extra: readability
Requires-Dist: textstat<0.8,>=0.7; extra == "readability"
Provides-Extra: vocalacoustics
Requires-Dist: praat-parselmouth>=0.4.6; extra == "vocalacoustics"
Requires-Dist: disvoice>=0.1.10; extra == "vocalacoustics"
Dynamic: license-file
